eole/__init__.py
eole/constants.py
eole/inference_engine.py
eole/train_single.py
eole/trainer.py
eole/adapters/__init__.py
eole/adapters/adapters.py
eole/bin/__init__.py
eole/bin/main.py
eole/bin/convert/HF_mappings.py
eole/bin/convert/__init__.py
eole/bin/convert/convert_HF.py
eole/bin/convert/convert_T5.py
eole/bin/convert/convert_onmt_config.py
eole/bin/run/__init__.py
eole/bin/run/build_vocab.py
eole/bin/run/predict.py
eole/bin/run/serve.py
eole/bin/run/train.py
eole/bin/tools/LM_scoring.py
eole/bin/tools/__init__.py
eole/bin/tools/embeddings_to_torch.py
eole/bin/tools/hellaswag.py
eole/bin/tools/load_test.py
eole/bin/tools/mbr_bleu.py
eole/bin/tools/oracle_bleu.py
eole/bin/tools/oracle_comet.py
eole/bin/tools/run_mmlu.py
eole/bin/tools/spm_to_vocab.py
eole/config/__init__.py
eole/config/cli.py
eole/config/common.py
eole/config/config.py
eole/config/data.py
eole/config/inference.py
eole/config/models.py
eole/config/run.py
eole/config/training.py
eole/decoders/__init__.py
eole/decoders/cnn_decoder.py
eole/decoders/decoder.py
eole/decoders/ensemble.py
eole/decoders/rnn_decoder.py
eole/decoders/transformer.py
eole/encoders/__init__.py
eole/encoders/cnn_encoder.py
eole/encoders/deepseek_sam.py
eole/encoders/encoder.py
eole/encoders/mean_encoder.py
eole/encoders/rnn_encoder.py
eole/encoders/transformer.py
eole/encoders/vision.py
eole/inputters/__init__.py
eole/inputters/dynamic_iterator.py
eole/inputters/image_utils.py
eole/inputters/inputter.py
eole/inputters/text_corpus.py
eole/inputters/text_utils.py
eole/models/__init__.py
eole/models/model.py
eole/models/model_saver.py
eole/predict/__init__.py
eole/predict/beam_search.py
eole/predict/decode_strategy.py
eole/predict/encoder.py
eole/predict/generator.py
eole/predict/greedy_search.py
eole/predict/inference.py
eole/predict/penalties.py
eole/predict/prediction.py
eole/predict/translator.py
eole/scorers/__init__.py
eole/scorers/bleu.py
eole/scorers/scorer.py
eole/scorers/ter.py
eole/tests/__init__.py
eole-0.4.4.dist-info/LICENSE.md
eole-0.4.4.dist-info/METADATA
eole-0.4.4.dist-info/WHEEL
eole-0.4.4.dist-info/entry_points.txt
eole-0.4.4.dist-info/top_level.txt
eole-0.4.4.dist-info/RECORD
