Metadata-Version: 2.1
Name: eole
Version: 0.4.4
Summary: Open language modeling toolkit based on PyTorch
Project-URL: Source, https://github.com/eole-nlp/eole/
Requires-Python: >=3.10
License-File: LICENSE.md
Requires-Dist: configargparse
Requires-Dist: ctranslate2<5,>=4
Requires-Dist: fastapi
Requires-Dist: fasttext-wheel
Requires-Dist: huggingface-hub
Requires-Dist: datasets
Requires-Dist: numpy>=2.0
Requires-Dist: pandas
Requires-Dist: protobuf==3.20.1
Requires-Dist: pyahocorasick
Requires-Dist: pyonmttok<2,>=1.38.1
Requires-Dist: pyyaml
Requires-Dist: rapidfuzz
Requires-Dist: rich
Requires-Dist: sacrebleu
Requires-Dist: safetensors
Requires-Dist: sentencepiece<0.1.98,>=0.1.94
Requires-Dist: six
Requires-Dist: spacy
Requires-Dist: subword-nmt>=0.3.7
Requires-Dist: tensorboard>=2.18.0
Requires-Dist: torch<2.10,>=2.8
Requires-Dist: torch-optimi
Requires-Dist: uvicorn
Requires-Dist: waitress
Requires-Dist: pydantic
